{"1": [{"lat": 19.14, "lng": 72.96000000000001, "count": 1.0}], "2": [{"lat": 19.227, "lng": 72.8805, "count": 1.0}], "11": [{"lat": 19.0485, "lng": 72.8325, "count": 1.0}, {"lat": 19.224, "lng": 72.777, "count": 2.0}], "12": [{"lat": 19.14, "lng": 72.96000000000001, "count": 10.0}, {"lat": 19.1415, "lng": 72.9645, "count": 1.0}, {"lat": 19.1475, "lng": 72.9615, "count": 1.0}, {"lat": 19.152, "lng": 72.9555, "count": 3.0}, {"lat": 19.209, "lng": 72.9105, "count": 3.0}, {"lat": 19.212, "lng": 72.912, "count": 1.0}]}